langhuan/__init__.py
langhuan/flask_starter.py
langhuan/history.py
langhuan/hyperflask.py
langhuan/options.py
langhuan/order_strategies.py
langhuan/progress.py
langhuan/tasks.py
langhuan/utility.py
langhuan/version.py
langhuan/loaders/__init__.py
langhuan/loaders/pytorch.py
langhuan/static/.DS_Store
langhuan/static/configs/README.md
langhuan/static/css/bootstrap.css
langhuan/static/css/bootstrap.css.map
langhuan/static/js/all.js
langhuan/static/js/bootstrap.min.js
langhuan/static/js/d3.js
langhuan/static/js/jquery.min.js
langhuan/static/js/popper.min.js
langhuan/templates/admin.html
langhuan/templates/base.html
langhuan/templates/classify.html
langhuan/templates/ner.html
langhuan/templates/tagging.html
langhuan-0.1.12.dist-info/METADATA
langhuan-0.1.12.dist-info/WHEEL
langhuan-0.1.12.dist-info/entry_points.txt
langhuan-0.1.12.dist-info/top_level.txt
langhuan-0.1.12.dist-info/RECORD
