Metadata-Version: 2.1
Name: langhuan
Version: 0.1.12
Summary: Language Human Annotation
Home-page: https://github.com/raynardj/langhuan
Author: xiaochen(ray) zhang
Author-email: b2ray2c@gmail.com
License: Apache Software License 2.0
Keywords: python pandas label data science
Platform: UNKNOWN
Classifier: Development Status :: 3 - Alpha
Classifier: Intended Audience :: Developers
Classifier: License :: OSI Approved :: Apache Software License
Classifier: Natural Language :: English
Classifier: Programming Language :: Python :: 3.6
Classifier: Programming Language :: Python :: 3.7
Classifier: Programming Language :: Python :: 3.8
Requires-Python: >=3.6
